{
  "cc0": 36727,
  "copyrighted": 22428,
  "other": 5678,
  "id": 64833,
  "accession_number": 63765,
  "share_license_status": 64833,
  "tombstone": 64833,
  "current_location": 4417,
  "title": 64833,
  "title_in_original_language": 1266,
  "series": 3545,
  "series_in_original_language": 100,
  "creation_date": 58554,
  "creation_date_earliest": 57947,
  "creation_date_latest": 57816,
  "creators": 46287,
  "culture": 64247,
  "technique": 64042,
  "support_materials": 6466,
  "department": 64833,
  "collection": 64833,
  "type": 64833,
  "measurements": 45779,
  "dimensions": 46884,
  "state_of_the_work": 3398,
  "edition_of_the_work": 1606,
  "creditline": 63892,
  "copyright": 7633,
  "inscriptions": 16722,
  "exhibitions": 24353,
  "provenance": 22400,
  "find_spot": 32,
  "related_works": 491,
  "former_accession_numbers": 6570,
  "fun_fact": 4386,
  "digital_description": 3957,
  "wall_description": 12073,
  "external_resources": 63502,
  "citations": 11917,
  "catalogue_raisonne": 12513,
  "url": 64833,
  "images": 34770,
  "num_artworks": 64833
}