{
  "cc0": 41424,
  "copyrighted": 26594,
  "other": 0,
  "id": 68018,
  "accession_number": 68018,
  "share_license_status": 68018,
  "legal_status": 68018,
  "tombstone": 68018,
  "current_location": 4244,
  "title": 68018,
  "accession_date": 67586,
  "sortable_date": 66219,
  "date_text": 68018,
  "creation_date": 66289,
  "creation_date_earliest": 66219,
  "creation_date_latest": 66077,
  "artists_tags": 47886,
  "creators": 48010,
  "culture": 67653,
  "technique": 67426,
  "support_materials": 6514,
  "department": 68018,
  "collection": 68018,
  "type": 68018,
  "measurements": 49985,
  "dimensions": 50671,
  "state_of_the_work": 3533,
  "edition_of_the_work": 2155,
  "copyright": 8292,
  "inscriptions": 18843,
  "exhibitions": 27426,
  "provenance": 29777,
  "find_spot": 23,
  "related_works": 1484,
  "former_accession_numbers": 7208,
  "did_you_know": 10254,
  "digital_description": 7051,
  "wall_description": 15568,
  "conservation_statement": 104,
  "external_resources": 68018,
  "citations": 20304,
  "url": 68018,
  "images": 40803,
  "alternate_images": 18164,
  "secondary_assets": 0,
  "creditline": 68017,
  "collapse_artists": 3055,
  "on_loan": 86,
  "recently_acquired": 1895,
  "record_type": 68018,
  "cover_accession_number": 23287,
  "is_nazi_era_provenance": 471,
  "zoomify_disabled": 20948,
  "impression": 1771,
  "sketchfab_id": 388,
  "sketchfab_url": 388,
  "has_artlens_media": 522,
  "has_artlens_scannable": 300,
  "alternate_titles": 8534,
  "upcoming_loans": 29,
  "current_loan": 29,
  "dimensions_searchable": 50671,
  "is_highlight": 296,
  "last_updated_in_athena": 68018,
  "current_exhibition": 221,
  "book_viewer_type": 0,
  "is_book_viewer": 0,
  "collection_mapped": 68005,
  "medium_mapped": 67441,
  "gallery_donor_text": 916,
  "catalogue_raisonne": 12675,
  "series": 4826,
  "title_in_original_language": 1882,
  "series_in_original_language": 189,
  "num_artworks": 68018
}