{
  "cc0": 38359,
  "copyrighted": 19929,
  "other": 5692,
  "id": 63980,
  "accession_number": 63979,
  "share_license_status": 63980,
  "tombstone": 63980,
  "current_location": 4372,
  "title": 63980,
  "title_in_original_language": 1340,
  "series": 3630,
  "series_in_original_language": 107,
  "creation_date": 58467,
  "creation_date_earliest": 58459,
  "creation_date_latest": 58328,
  "creators": 45778,
  "culture": 63789,
  "technique": 63283,
  "support_materials": 6471,
  "department": 63980,
  "collection": 63980,
  "type": 63980,
  "measurements": 45446,
  "dimensions": 46425,
  "state_of_the_work": 3414,
  "edition_of_the_work": 1659,
  "creditline": 63979,
  "copyright": 7277,
  "inscriptions": 17208,
  "exhibitions": 24535,
  "provenance": 23395,
  "find_spot": 34,
  "related_works": 516,
  "former_accession_numbers": 7025,
  "fun_fact": 5260,
  "digital_description": 4629,
  "wall_description": 12548,
  "external_resources": 63969,
  "citations": 12998,
  "catalogue_raisonne": 12521,
  "url": 63980,
  "images": 36933,
  "num_artworks": 63980
}