{
  "cc0": 37278,
  "copyrighted": 26886,
  "other": 1,
  "id": 64165,
  "accession_number": 64165,
  "share_license_status": 64165,
  "tombstone": 64165,
  "current_location": 4247,
  "title": 64165,
  "title_in_original_language": 1430,
  "series": 3693,
  "series_in_original_language": 120,
  "creation_date": 58732,
  "creation_date_earliest": 58725,
  "creation_date_latest": 58595,
  "creators": 45921,
  "culture": 63975,
  "technique": 63470,
  "support_materials": 6480,
  "department": 64165,
  "collection": 64165,
  "type": 64165,
  "measurements": 46142,
  "dimensions": 46698,
  "state_of_the_work": 3482,
  "edition_of_the_work": 1751,
  "creditline": 64164,
  "copyright": 7396,
  "inscriptions": 17602,
  "exhibitions": 24705,
  "provenance": 24225,
  "find_spot": 37,
  "related_works": 566,
  "former_accession_numbers": 7036,
  "fun_fact": 5863,
  "digital_description": 5119,
  "wall_description": 12997,
  "external_resources": 64154,
  "citations": 13647,
  "catalogue_raisonne": 12583,
  "url": 64165,
  "images": 36382,
  "sketchfab_id": 38,
  "sketchfab_url": 38,
  "num_artworks": 64165
}