{
  "cc0": 39432,
  "copyrighted": 27208,
  "other": 0,
  "id": 66640,
  "accession_number": 66640,
  "share_license_status": 66640,
  "legal_status": 66640,
  "tombstone": 66640,
  "current_location": 4653,
  "title": 66640,
  "accession_date": 66210,
  "sortable_date": 62666,
  "date_text": 66640,
  "creation_date": 62679,
  "creation_date_earliest": 62666,
  "creation_date_latest": 62527,
  "artists_tags": 47039,
  "creators": 47166,
  "culture": 66282,
  "technique": 65950,
  "support_materials": 6510,
  "department": 66640,
  "collection": 66640,
  "type": 66640,
  "measurements": 48471,
  "dimensions": 49018,
  "state_of_the_work": 3494,
  "edition_of_the_work": 1978,
  "copyright": 8276,
  "inscriptions": 18106,
  "exhibitions": 26072,
  "provenance": 27249,
  "find_spot": 40,
  "related_works": 1089,
  "former_accession_numbers": 7173,
  "did_you_know": 8006,
  "digital_description": 5996,
  "wall_description": 14650,
  "conservation_statement": 60,
  "external_resources": 66640,
  "citations": 16943,
  "url": 66640,
  "images": 38241,
  "alternate_images": 17322,
  "secondary_assets": 0,
  "creditline": 66639,
  "collapse_artists": 3010,
  "on_loan": 82,
  "recently_acquired": 2118,
  "record_type": 66640,
  "cover_accession_number": 22137,
  "is_nazi_era_provenance": 471,
  "zoomify_disabled": 21824,
  "impression": 1765,
  "sketchfab_id": 229,
  "sketchfab_url": 229,
  "has_artlens_media": 520,
  "has_artlens_scannable": 294,
  "alternate_titles": 8173,
  "upcoming_loans": 130,
  "dimensions_searchable": 49018,
  "is_highlight": 294,
  "last_updated_in_athena": 66640,
  "current_exhibition": 448,
  "book_viewer_type": 0,
  "is_book_viewer": 0,
  "collection_mapped": 66627,
  "medium_mapped": 60068,
  "catalogue_raisonne": 12623,
  "series": 4360,
  "title_in_original_language": 1599,
  "series_in_original_language": 175,
  "num_artworks": 66640
}